{
    "resourceType": "Specimen",
    "id": "234",
    "meta": {
        "profile":  [
            "http://highmed.org/fhir/StructureDefinition/ic/Specimen"
        ]
    },

    "accessionIdentifier":  [
        {
            "system": "https://www.charite.de/fhir/CodeSystem/lab-identifiers",
            "assigner": {
            "reference": "Organization/Charite"
            }
        }
    ],    

    "type": {
                "coding":  [
                    {
                        "system": "http://snomed.info/sct",
                        "code": "123038009"
                    }
                ]
            },
    "subject": {
        "reference": "Patient/123"
    },

    "collection": 
        {

        "collectedDateTime": "2021-05-16T08:49:21+02:00",
        "bodySite": 
        {
                "coding":  [
                    {
                        "system": "http://snomed.info/sct",
                        "code": "53505006"
                    }
                ]
        }
    }

}